files/__init__.py
files/temp/__init__.py
files/temp/cache/__init__.py
files/temp/cache/template.py
files/temp/cache/user.py
pyxa/__init__.py
pyxa/constants.py
pyxa/parser.py
pyxa/cli/__init__.py
pyxa/cli/arguments.py
pyxa/cli/formatter.py
pyxa/cli/options.py
pyxa/cli/strings.py
pyxa/cli/commands/__init__.py
pyxa/cli/commands/create.py
pyxa/cli/commands/project_template/__init__.py
pyxa/cli/commands/project_template/files/__init__.py
pyxa/cli/commands/project_template/files/temp/__init__.py
pyxa/cli/commands/project_template/files/temp/cache/__init__.py
pyxa/cli/commands/project_template/frontend/__init__.py
pyxa/cli/commands/project_template/user/__init__.py
pyxa/core/__init__.py
pyxa/core/location.py
pyxa/core/weather.py
pyxa/files/__init__.py
pyxa/files/temp/__init__.py
pyxa/files/temp/cache/__init__.py
pyxa/tests/__init__.py
pyxa/utils/__init__.py
pyxa/utils/common.py
pyxa/utils/dataset.py
pyxa/utils/exceptions.py
pyxa/utils/settings.py
pyxa/utils/system.py
pyxa/utils/user.py
tests/__init__.py
pyxa-0.0.2.dist-info/LICENSE
pyxa-0.0.2.dist-info/METADATA
pyxa-0.0.2.dist-info/WHEEL
pyxa-0.0.2.dist-info/entry_points.txt
pyxa-0.0.2.dist-info/top_level.txt
pyxa-0.0.2.dist-info/RECORD
