Metadata-Version: 2.1
Name: pyxa
Version: 0.0.2
Summary: pyXA is an open-source, flexible, high-performance function serving framework for Charlotte AI.
Home-page: https://github.com/xames3/pyxa/
Author: XA
Author-email: xames3.developer@gmail.com
Maintainer: XA
Maintainer-email: xames3.developer@gmail.com
License: Apache 2.0
Download-URL: https://github.com/xames3/pyxa/tags
Keywords: pyxa charlotte ai artificial intelligence
Platform: UNKNOWN
Classifier: Development Status :: 3 - Alpha
Classifier: Intended Audience :: Developers
Classifier: Intended Audience :: Science/Research
Classifier: License :: OSI Approved :: Apache Software License
Classifier: Operating System :: Microsoft :: Windows :: Windows 10
Classifier: Programming Language :: Python :: 3.5
Classifier: Programming Language :: Python :: 3.6
Classifier: Programming Language :: Python :: 3.7
Classifier: Programming Language :: Python :: 3.8
Classifier: Programming Language :: Python :: 3 :: Only
Classifier: Topic :: Communications :: Chat
Classifier: Topic :: Scientific/Engineering
Classifier: Topic :: Scientific/Engineering :: Artificial Intelligence
Classifier: Topic :: Software Development
Classifier: Topic :: Software Development :: Libraries
Classifier: Topic :: Software Development :: Libraries :: Python Modules
Requires-Python: ~=3.5
